biptools/__init__.py
biptools/bip32.py
biptools/bip39.py
biptools/bip44.py
biptools/bip49.py
biptools/bip84.py
biptools/entropy.py
biptools/secp256k1.py
biptools/seeds.py
bip_tools-1.0.4.dist-info/METADATA
bip_tools-1.0.4.dist-info/WHEEL
bip_tools-1.0.4.dist-info/top_level.txt
bip_tools-1.0.4.dist-info/RECORD
