Metadata-Version: 2.1
Name: bip-tools
Version: 1.0.4
Summary: Manage BIP32 based HD wallets.
Home-page: https://github.com/gavinbrrtt/biptools
Author: Gavin Barrett
Author-email: gavinbrrtt@gmail.com
License: GPLv3
Platform: UNKNOWN
Classifier: License :: OSI Approved :: GNU General Public License v3 (GPLv3)
Classifier: Programming Language :: Python :: 3
Classifier: Programming Language :: Python :: 3.8
Requires-Dist: base58
